littletree/__init__.py
littletree/basenode.py
littletree/exceptions.py
littletree/node.py
littletree/treemixin.py
littletree/serializers/__init__.py
littletree/serializers/_nodeeditor.py
littletree/serializers/dictserializer.py
littletree/serializers/networkxserializer.py
littletree/serializers/newickserializer.py
littletree/serializers/relationserializer.py
littletree/serializers/rowserializer.py
littletree-0.9.1.dist-info/licenses/LICENSE
littletree-0.9.1.dist-info/METADATA
littletree-0.9.1.dist-info/WHEEL
littletree-0.9.1.dist-info/top_level.txt
littletree-0.9.1.dist-info/RECORD
