Metadata-Version: 2.4
Name: littletree
Version: 0.9.1
Summary: Tree library
Author-email: lverweijen <lauwerund@gmail.com>
License-Expression: Apache-2.0
Project-URL: Homepage, https://github.com/lverweijen/littletree
Project-URL: Documentation, https://lverweijen.github.io/littletree
Project-URL: Repository, https://github.com/lverweijen/littletree
Project-URL: Issues, https://github.com/lverweijen/littletree/issues
Project-URL: Changelog, https://lverweijen.github.io/littletree/changelog.html
Keywords: tree,datastructure,hierarchy,taxonomy,newick,graphviz,mermaid
Classifier: Intended Audience :: Developers
Classifier: Intended Audience :: Science/Research
Classifier: Operating System :: OS Independent
Classifier: Programming Language :: Python :: 3
Classifier: Programming Language :: Python :: 3.10
Classifier: Programming Language :: Python :: 3.11
Classifier: Programming Language :: Python :: 3.12
Classifier: Programming Language :: Python :: 3.13
Classifier: Typing :: Typed
Requires-Python: >=3.10
License-File: LICENSE
Requires-Dist: abstracttree>=0.2.0
Provides-Extra: export
Requires-Dist: Pillow>=5.0; extra == "export"
Requires-Dist: matplotlib>=3.0; extra == "export"
Requires-Dist: svglib>=1.5.0; extra == "export"
Dynamic: license-file
